{
    "version": {
        "id": 1736179,
        "crate": "zksync_proof_data_handler",
        "num": "29.3.0-non-semver-compat",
        "dl_path": "/api/v1/crates/zksync_proof_data_handler/29.3.0-non-semver-compat/download",
        "readme_path": "/api/v1/crates/zksync_proof_data_handler/29.3.0-non-semver-compat/readme",
        "updated_at": "2025-09-18T22:06:55.899514Z",
        "created_at": "2025-09-18T22:06:55.899514Z",
        "downloads": 281,
        "features": {},
        "yanked": false,
        "yank_message": null,
        "lib_links": null,
        "license": "MIT OR Apache-2.0",
        "links": {
            "dependencies": "/api/v1/crates/zksync_proof_data_handler/29.3.0-non-semver-compat/dependencies",
            "version_downloads": "/api/v1/crates/zksync_proof_data_handler/29.3.0-non-semver-compat/downloads",
            "authors": "/api/v1/crates/zksync_proof_data_handler/29.3.0-non-semver-compat/authors"
        },
        "crate_size": 51233,
        "published_by": {
            "id": 297400,
            "login": "CratesMatterLabs",
            "name": null,
            "avatar": "https://avatars.githubusercontent.com/u/185927582?v=4",
            "url": "https://github.com/CratesMatterLabs"
        },
        "audit_actions": [
            {
                "action": "publish",
                "user": {
                    "id": 297400,
                    "login": "CratesMatterLabs",
                    "name": null,
                    "avatar": "https://avatars.githubusercontent.com/u/185927582?v=4",
                    "url": "https://github.com/CratesMatterLabs"
                },
                "time": "2025-09-18T22:06:55.899514Z"
            }
        ],
        "checksum": "b7407e6003f85d620aa7cea607d6af284ac2ff2a2000a9ed45cd65da61f0f965",
        "rust_version": null,
        "has_lib": true,
        "bin_names": [],
        "edition": "2021",
        "description": "ZKsync proof data handler API",
        "homepage": "https://zksync.io/",
        "documentation": null,
        "repository": "https://github.com/matter-labs/zksync-era",
        "trustpub_data": null,
        "linecounts": {
            "languages": {
                "Rust": {
                    "code_lines": 867,
                    "comment_lines": 5,
                    "files": 10
                }
            },
            "total_code_lines": 867,
            "total_comment_lines": 5
        }
    }
}