{
    "version": {
        "id": 1472670,
        "crate": "zksync_snapshots_applier",
        "num": "26.7.0-non-semver-compat",
        "dl_path": "/api/v1/crates/zksync_snapshots_applier/26.7.0-non-semver-compat/download",
        "readme_path": "/api/v1/crates/zksync_snapshots_applier/26.7.0-non-semver-compat/readme",
        "updated_at": "2025-03-06T23:31:32.118176Z",
        "created_at": "2025-03-06T23:31:32.118176Z",
        "downloads": 637,
        "features": {},
        "yanked": false,
        "yank_message": null,
        "lib_links": null,
        "license": "MIT OR Apache-2.0",
        "links": {
            "dependencies": "/api/v1/crates/zksync_snapshots_applier/26.7.0-non-semver-compat/dependencies",
            "version_downloads": "/api/v1/crates/zksync_snapshots_applier/26.7.0-non-semver-compat/downloads",
            "authors": "/api/v1/crates/zksync_snapshots_applier/26.7.0-non-semver-compat/authors"
        },
        "crate_size": 17432,
        "published_by": {
            "id": 297400,
            "login": "CratesMatterLabs",
            "name": null,
            "avatar": "https://avatars.githubusercontent.com/u/185927582?v=4",
            "url": "https://github.com/CratesMatterLabs"
        },
        "audit_actions": [
            {
                "action": "publish",
                "user": {
                    "id": 297400,
                    "login": "CratesMatterLabs",
                    "name": null,
                    "avatar": "https://avatars.githubusercontent.com/u/185927582?v=4",
                    "url": "https://github.com/CratesMatterLabs"
                },
                "time": "2025-03-06T23:31:32.118176Z"
            }
        ],
        "checksum": "47ee605e14327c74a96cab2216b4d0238540ed3f1472e0a22107d8c2377c04bb",
        "rust_version": null,
        "has_lib": true,
        "bin_names": [],
        "edition": "2021",
        "description": "Library for applying ZKsync state snapshots",
        "homepage": "https://zksync.io/",
        "documentation": null,
        "repository": "https://github.com/matter-labs/zksync-era",
        "trustpub_data": null,
        "linecounts": {
            "languages": {
                "Rust": {
                    "code_lines": 913,
                    "comment_lines": 22,
                    "files": 2
                }
            },
            "total_code_lines": 913,
            "total_comment_lines": 22
        }
    }
}