{
    "version": {
        "id": 1110762,
        "crate": "zng-wgt-data",
        "num": "0.2.3",
        "dl_path": "/api/v1/crates/zng-wgt-data/0.2.3/download",
        "readme_path": "/api/v1/crates/zng-wgt-data/0.2.3/readme",
        "updated_at": "2024-04-10T20:30:09.440883Z",
        "created_at": "2024-04-10T20:30:09.440883Z",
        "downloads": 1131,
        "features": {},
        "yanked": false,
        "yank_message": null,
        "lib_links": null,
        "license": "Apache-2.0 OR MIT",
        "links": {
            "dependencies": "/api/v1/crates/zng-wgt-data/0.2.3/dependencies",
            "version_downloads": "/api/v1/crates/zng-wgt-data/0.2.3/downloads",
            "authors": "/api/v1/crates/zng-wgt-data/0.2.3/authors"
        },
        "crate_size": 6711,
        "published_by": {
            "id": 80740,
            "login": "SamRodri",
            "name": "Samuel",
            "avatar": "https://avatars.githubusercontent.com/u/449925?v=4",
            "url": "https://github.com/SamRodri"
        },
        "audit_actions": [
            {
                "action": "publish",
                "user": {
                    "id": 80740,
                    "login": "SamRodri",
                    "name": "Samuel",
                    "avatar": "https://avatars.githubusercontent.com/u/449925?v=4",
                    "url": "https://github.com/SamRodri"
                },
                "time": "2024-04-10T20:30:09.440883Z"
            }
        ],
        "checksum": "08a38ecf675a04eb723deece0fdaf28ca74dc7181a4fce284e20c0f1bf1182b8",
        "rust_version": null,
        "has_lib": true,
        "bin_names": [],
        "edition": "2021",
        "description": "Part of the zng project.",
        "homepage": null,
        "documentation": "https://zng-ui.github.io/doc/zng_wgt_data",
        "repository": "https://github.com/zng-ui/zng",
        "trustpub_data": null,
        "linecounts": {
            "languages": {
                "Rust": {
                    "code_lines": 461,
                    "comment_lines": 2,
                    "files": 1
                }
            },
            "total_code_lines": 461,
            "total_comment_lines": 2
        }
    }
}